bitflow/__init__.py
bitflow/batch.py
bitflow/driver.py
bitflow/pipeline.py
bitflow/scheduler.py
bitflow/utils/__init__.py
bitflow/utils/BatchLearner.py
bitflow/utils/BatchTorchLearner.py
bitflow/utils/create_dependencies.py
bitflow/utils/dashboard.py
bitflow/utils/log.py
bitflow/utils/module.py
bitflow/utils/OnlineLearner.py
bitflow/utils/OnlineTorchLearner.py
bitflow/utils/profile.py
bitflow/utils/silence.py
bitflow/utils/transaction.py
bitflow/utils/utils.py
bitflow-0.6.0.dist-info/WHEEL
bitflow-0.6.0.dist-info/METADATA
bitflow-0.6.0.dist-info/RECORD
